setup.py
tornpsql/__init__.py
tornpsql/pubsub.py
tornpsql.egg-info/PKG-INFO
tornpsql.egg-info/SOURCES.txt
tornpsql.egg-info/dependency_links.txt
tornpsql.egg-info/requires.txt
tornpsql.egg-info/top_level.txt
tornpsql.egg-info/zip-safe