Metadata-Version: 1.1
Name: tornpsql
Version: 0.1.1
Summary: PostgreSQL handler for Tornado Web
Home-page: https://github.com/stevepeak/tornpsql
Author: @iopeak
Author-email: steve@stevepeak.net
License: Apache v2.0
Keywords: tornado psql postgres postgresql sql
Platform: UNKNOWN
Classifier: Development Status :: 5 - Production/Stable
Classifier: License :: OSI Approved :: Apache Software License
Classifier: Programming Language :: Python :: 2.7
Classifier: Programming Language :: SQL
Classifier: Topic :: Database
